mcgrad/__init__.py
mcgrad/_compat.py
mcgrad/_segmentation.py
mcgrad/_utils.py
mcgrad/base.py
mcgrad/methods.py
mcgrad/metrics.py
mcgrad/plotting.py
mcgrad/tuning.py
mcgrad/tests/__init__.py
mcgrad/tests/conftest.py
mcgrad/tests/pytest.ini
mcgrad/tests/test_compat.py
mcgrad/tests/test_methods.py
mcgrad/tests/test_metrics.py
mcgrad/tests/test_plotting.py
mcgrad/tests/test_segmentation.py
mcgrad/tests/test_tuning.py
mcgrad/tests/test_utils.py
mcgrad-0.1.1.dist-info/licenses/LICENSE
mcgrad-0.1.1.dist-info/METADATA
mcgrad-0.1.1.dist-info/WHEEL
mcgrad-0.1.1.dist-info/top_level.txt
mcgrad-0.1.1.dist-info/RECORD
