Metadata-Version: 2.4
Name: MCGrad
Version: 0.1.1
Summary: Production-ready multicalibration for machine learning
Author: Meta Platforms, Inc.
License: MIT
Project-URL: Homepage, https://mcgrad.dev
Project-URL: Documentation, https://mcgrad.readthedocs.io
Project-URL: Repository, https://github.com/facebookincubator/MCGrad
Project-URL: Issues, https://github.com/facebookincubator/MCGrad/issues
Keywords: calibration,multicalibration,machine-learning,fairness,probability-calibration
Classifier: Development Status :: 4 - Beta
Classifier: Intended Audience :: Developers
Classifier: Intended Audience :: Science/Research
Classifier: License :: OSI Approved :: MIT License
Classifier: Operating System :: OS Independent
Classifier: Programming Language :: Python :: 3
Classifier: Programming Language :: Python :: 3.10
Classifier: Programming Language :: Python :: 3.11
Classifier: Programming Language :: Python :: 3.12
Classifier: Topic :: Scientific/Engineering :: Artificial Intelligence
Classifier: Topic :: Scientific/Engineering :: Information Analysis
Classifier: Typing :: Typed
Requires-Python: >=3.10
License-File: LICENSE
Requires-Dist: numpy>=1.20.0
Requires-Dist: pandas>=1.3.0
Requires-Dist: scipy>=1.7.0
Requires-Dist: scikit-learn>=1.0.0
Requires-Dist: torch>=1.9.0
Requires-Dist: lightgbm>=3.0.0
Requires-Dist: plotly>=5.0.0
Requires-Dist: pyarrow>=10.0.0
Requires-Dist: cffi>=1.15.0
Requires-Dist: ax-platform>=1.2.1
Requires-Dist: psutil>=7.1.0
Provides-Extra: dev
Requires-Dist: pytest>=8.0.0; extra == "dev"
Requires-Dist: pytest-cov>=4.0.0; extra == "dev"
Requires-Dist: flake8==7.3.0; extra == "dev"
Requires-Dist: flake8-bugbear>=24.0.0; extra == "dev"
Requires-Dist: papermill>=2.4.0; extra == "dev"
Provides-Extra: tutorials
Requires-Dist: notebook>=7.0.0; extra == "tutorials"
Requires-Dist: jupyterlab>=4.0.0; extra == "tutorials"
Requires-Dist: folktables>=0.0.12; extra == "tutorials"
Provides-Extra: docs
Requires-Dist: sphinx>=7.0.0; extra == "docs"
Requires-Dist: sphinx-rtd-theme>=2.0.0; extra == "docs"
Requires-Dist: sphinx-autodoc-typehints>=1.25.0; extra == "docs"
Dynamic: license-file
